sebaubuntu_libs/__init__.py
sebaubuntu_libs/libaik/__init__.py
sebaubuntu_libs/libandroid/__init__.py
sebaubuntu_libs/libandroid/device_info.py
sebaubuntu_libs/libandroid/elf/__init__.py
sebaubuntu_libs/libandroid/elf/elf.py
sebaubuntu_libs/libandroid/elf/shared_library.py
sebaubuntu_libs/libandroid/fstab/__init__.py
sebaubuntu_libs/libandroid/partitions/__init__.py
sebaubuntu_libs/libandroid/partitions/partition.py
sebaubuntu_libs/libandroid/partitions/partition_model.py
sebaubuntu_libs/libandroid/partitions/partitions.py
sebaubuntu_libs/libandroid/props/__init__.py
sebaubuntu_libs/libandroid/props/utils.py
sebaubuntu_libs/libandroid/versions.py
sebaubuntu_libs/libandroid/vintf/__init__.py
sebaubuntu_libs/libandroid/vintf/aidl.py
sebaubuntu_libs/libandroid/vintf/common.py
sebaubuntu_libs/libandroid/vintf/hidl.py
sebaubuntu_libs/libandroid/vintf/manifest.py
sebaubuntu_libs/libcompat/__init__.py
sebaubuntu_libs/libcompat/distutils/__init__.py
sebaubuntu_libs/libcompat/distutils/_modified.py
sebaubuntu_libs/libcompat/distutils/dir_util.py
sebaubuntu_libs/libcompat/distutils/errors.py
sebaubuntu_libs/libcompat/distutils/file_util.py
sebaubuntu_libs/libcompat/distutils/util.py
sebaubuntu_libs/libexception/__init__.py
sebaubuntu_libs/libgofile/__init__.py
sebaubuntu_libs/libgofile/account.py
sebaubuntu_libs/libgofile/contents.py
sebaubuntu_libs/libgofile/raw_api/__init__.py
sebaubuntu_libs/libgofile/raw_api/rest.py
sebaubuntu_libs/libgofile/session.py
sebaubuntu_libs/libgofile/utils.py
sebaubuntu_libs/liblocale/__init__.py
sebaubuntu_libs/liblogging/__init__.py
sebaubuntu_libs/libnekobin/__init__.py
sebaubuntu_libs/libpath/__init__.py
sebaubuntu_libs/libreorder/__init__.py
sebaubuntu_libs/libsed/__init__.py
sebaubuntu_libs/libstring/__init__.py
sebaubuntu_libs/libtyping/__init__.py
sebaubuntu_libs-1.6.0.dist-info/METADATA
sebaubuntu_libs-1.6.0.dist-info/WHEEL
sebaubuntu_libs-1.6.0.dist-info/RECORD
