Metadata-Version: 2.4
Name: sebaubuntu_libs
Version: 1.6.0
Summary: SebaUbuntu's shared libs
License: Apache-2.0
Author: Sebastiano Barezzi
Author-email: seba@sebaubuntu.dev
Requires-Python: >=3.9,<4.0
Classifier: License :: OSI Approved :: Apache Software License
Classifier: Programming Language :: Python :: 3
Classifier: Programming Language :: Python :: 3.9
Classifier: Programming Language :: Python :: 3.10
Classifier: Programming Language :: Python :: 3.11
Classifier: Programming Language :: Python :: 3.12
Classifier: Programming Language :: Python :: 3.13
Classifier: Programming Language :: Python :: 3.14
Provides-Extra: docs
Requires-Dist: GitPython (>=3.1.27,<4.0.0)
Requires-Dist: pyelftools (>=0.29,<0.33)
Requires-Dist: requests (>=2.32.5,<3.0.0)
Requires-Dist: sphinx (>=5.0.1,<8.0.0) ; extra == "docs"
Requires-Dist: sphinx-rtd-theme (>=1,<4) ; extra == "docs"
Project-URL: Repository, https://github.com/sebaubuntu-python/sebaubuntu_libs
